yippee/__init__.py
yippee/__version__.py
yippee/cli.py
yippee/config.py
yippee/generator.py
yippee/repl.py
yippee-0.0.1.dist-info/METADATA
yippee-0.0.1.dist-info/WHEEL
yippee-0.0.1.dist-info/entry_points.txt
yippee-0.0.1.dist-info/top_level.txt
yippee-0.0.1.dist-info/RECORD
