Metadata-Version: 2.1
Name: yippee
Version: 0.0.1
Summary: Easily manage your requirements.txt files!
Home-page: https://github.com/joshbuddy/yippee
Author: joshbuddy
Author-email: joshbuddy@gmail.com
License: MIT
Platform: UNKNOWN
Classifier: License :: OSI Approved :: MIT License
Classifier: Programming Language :: Python
Classifier: Programming Language :: Python :: 3
Classifier: Programming Language :: Python :: 3.6
Classifier: Programming Language :: Python :: Implementation :: CPython
Classifier: Programming Language :: Python :: Implementation :: PyPy
Requires-Python: >=3.6.0
Requires-Dist: Click (==7.0)
